unisoc_unlock/__init__.py
unisoc_unlock/__main__.py
unisoc_unlock/cli.py
unisoc_unlock/rsa4096_vbmeta.pem
unisoc_unlock/bundled_adb/__init__.py
unisoc_unlock/bundled_adb/common.py
unisoc_unlock/bundled_adb/fastboot.py
unisoc_unlock/bundled_adb/usb_exceptions.py
unisoc_unlock-0.0.2.dist-info/METADATA
unisoc_unlock-0.0.2.dist-info/WHEEL
unisoc_unlock-0.0.2.dist-info/entry_points.txt
unisoc_unlock-0.0.2.dist-info/RECORD
