Metadata-Version: 2.1
Name: unisoc_unlock
Version: 0.0.2
Summary: Tool for (un)locking a Unisoc/Spreadtrum Android bootloader
Project-URL: Homepage, https://github.com/patrislav1/unisoc-unlock
Author-email: Patrick Huesmann <info@patrick-huesmann.de>
Requires-Python: >=3.6
Requires-Dist: libusb1
Requires-Dist: pycryptodome
